gfs_sampler/__init__.py
gfs_sampler/distributions.py
gfs_sampler/helpers.py
gfs_sampler/master.py
gfs_sampler-0.2.6.dist-info/METADATA
gfs_sampler-0.2.6.dist-info/WHEEL
gfs_sampler-0.2.6.dist-info/top_level.txt
gfs_sampler-0.2.6.dist-info/RECORD
