Metadata-Version: 2.1
Name: gfs-sampler
Version: 0.2.6
Summary: Sample permutations of one data set with respect to another data set within defined blocks for the purposes of computing statistics over a merged data set.
Home-page: https://pypi.org/project/gfs_sampler/
Author: Edwin Farley
Author-email: edwin_farley@alumni.brown.edu
License: UNKNOWN
Platform: UNKNOWN
Classifier: Programming Language :: Python :: 3
Classifier: License :: OSI Approved :: GNU General Public License v3 (GPLv3)
Classifier: Operating System :: OS Independent
Requires-Python: >=3.6, <3.8
Requires-Dist: theano (==1.0.4)
Requires-Dist: pymc3 (==3.6)
